farabio/Dockerfile
farabio/__init__.py
farabio/main.py
farabio/requirements.txt
farabio-2.0.0.dist-info/METADATA
farabio-2.0.0.dist-info/WHEEL
farabio-2.0.0.dist-info/licenses/LICENSE
farabio-2.0.0.dist-info/RECORD
