Metadata-Version: 2.3
Name: farabio
Version: 2.0.0
Summary: Python toolkit for AI-based biomedical image analysis
Project-URL: Homepage, https://github.com/tuttelikz/farabio
Project-URL: Documentation, https://farabio.readthedocs.io/en/latest/
Project-URL: Issues, https://github.com/tuttelikz/farabio/issues
Author-email: Sanzhar Askaruly <s.askaruly@gmail.com>
Maintainer-email: Sanzhar Askaruly <s.askaruly@gmail.com>
License:                     GNU GENERAL PUBLIC LICENSE
License-File: LICENSE
Keywords: datasets,deep learning,models,python,pytorch
Classifier: Programming Language :: Python :: 3
Requires-Python: >=3.8
Requires-Dist: scikit-image==0.24.0
Requires-Dist: scikit-learn==1.5.2
